CompDesc/CompDesc.py
CompDesc/__init__.py
CompDesc/functionToolbox.py
Desc1D2D/AtomProperty.py
Desc1D2D/AtomTypes.py
Desc1D2D/EStateGlobal.py
Desc1D2D/MQNs.py
Desc1D2D/__init__.py
Desc1D2D/basak.py
Desc1D2D/bcut.py
Desc1D2D/charge.py
Desc1D2D/connectivity.py
Desc1D2D/constitution.py
Desc1D2D/geary.py
Desc1D2D/kappa.py
Desc1D2D/moe.py
Desc1D2D/molproperty.py
Desc1D2D/moran.py
Desc1D2D/moreaubroto.py
Desc1D2D/morgan.py
Desc1D2D/topology.py
Desc3D/Atom3DProperty.py
Desc3D/__init__.py
Desc3D/asa3D.py
Desc3D/autocorrelation3D.py
Desc3D/cpsa3D.py
Desc3D/geo3D.py
Desc3D/getaway3D.py
Desc3D/morse3D.py
Desc3D/rdf3D.py
Desc3D/vector3d.py
Desc3D/whim3D.py
compdesc-1.0.7.dist-info/licenses/LICENCE
prepChem/__init__.py
prepChem/prepChem.py
tests/__init__.py
tests/fortest.py
tests/testChemical.py
compdesc-1.0.7.dist-info/METADATA
compdesc-1.0.7.dist-info/WHEEL
compdesc-1.0.7.dist-info/top_level.txt
compdesc-1.0.7.dist-info/RECORD
