Metadata-Version: 2.4
Name: CompDesc
Version: 1.0.7
Summary: Compute molecular descriptors 1D, 2D and 3D from a SMILES string ligand
Home-page: https://github.com/ABorrel/CompDESC
Author: Alexandre Borrel
Author-email: a.borrel@gmail.com
Classifier: Programming Language :: Python :: 3
Classifier: License :: OSI Approved :: MIT License
Classifier: Operating System :: OS Independent
Requires-Python: >=3.6
License-File: LICENCE
Dynamic: author
Dynamic: author-email
Dynamic: classifier
Dynamic: description
Dynamic: description-content-type
Dynamic: home-page
Dynamic: license-file
Dynamic: requires-python
Dynamic: summary
